MANIFEST.in
setup.py
doc/LICENSE
doc/README.rst
doc/build/html/.buildinfo
doc/build/html/background.xhtml
doc/build/html/developer-api.xhtml
doc/build/html/genindex.xhtml
doc/build/html/index.xhtml
doc/build/html/objects.inv
doc/build/html/overview.xhtml
doc/build/html/py-modindex.xhtml
doc/build/html/references.xhtml
doc/build/html/requirements.xhtml
doc/build/html/search.xhtml
doc/build/html/searchindex.js
doc/build/html/user-api.xhtml
doc/build/html/_modules/index.xhtml
doc/build/html/_modules/test.xhtml
doc/build/html/_modules/dunshire/cones.xhtml
doc/build/html/_modules/dunshire/errors.xhtml
doc/build/html/_modules/dunshire/games.xhtml
doc/build/html/_modules/dunshire/matrices.xhtml
doc/build/html/_modules/test/matrices_test.xhtml
doc/build/html/_modules/test/randomgen.xhtml
doc/build/html/_modules/test/symmetric_linear_game_test.xhtml
doc/build/html/_sources/background.txt
doc/build/html/_sources/developer-api.txt
doc/build/html/_sources/index.txt
doc/build/html/_sources/overview.txt
doc/build/html/_sources/references.txt
doc/build/html/_sources/requirements.txt
doc/build/html/_sources/user-api.txt
doc/build/html/_static/ajax-loader.gif
doc/build/html/_static/alabaster.css
doc/build/html/_static/basic.css
doc/build/html/_static/comment-bright.png
doc/build/html/_static/comment-close.png
doc/build/html/_static/comment.png
doc/build/html/_static/custom.css
doc/build/html/_static/doctools.js
doc/build/html/_static/down-pressed.png
doc/build/html/_static/down.png
doc/build/html/_static/file.png
doc/build/html/_static/jquery-1.11.1.js
doc/build/html/_static/jquery.js
doc/build/html/_static/minus.png
doc/build/html/_static/plus.png
doc/build/html/_static/pygments.css
doc/build/html/_static/searchtools.js
doc/build/html/_static/underscore-1.3.1.js
doc/build/html/_static/underscore.js
doc/build/html/_static/up-pressed.png
doc/build/html/_static/up.png
doc/build/html/_static/websupport.js
dunshire/__init__.py
dunshire/cones.py
dunshire/errors.py
dunshire/games.py
dunshire.egg-info/PKG-INFO
dunshire.egg-info/SOURCES.txt
dunshire.egg-info/dependency_links.txt
dunshire.egg-info/requires.txt
dunshire.egg-info/top_level.txt
