Metadata-Version: 1.1
Name: dunshire
Version: 0.1.1
Summary: A library for solving linear games over symmetric cones
Home-page: http://michael.orlitzky.com/code/dunshire/
Author: Michael Orlitzky
Author-email: michael@orlitzky.com
License: AGPLv3+
Keywords: game theory,cone programming,optimization
Platform: UNKNOWN
Classifier: Development Status :: 3 - Alpha
Classifier: Intended Audience :: Science/Research
Classifier: Programming Language :: Python :: 3.4
Classifier: Programming Language :: Python :: 3.5
